FlirImageExtractor/.git
FlirImageExtractor/README.md
FlirImageExtractor/__init__.py
FlirImageExtractor/flir_image_extractor.py
FlirImageExtractor/examples/ax8.jpg
FlirImageExtractor/examples/flir_example.jpg
FlirImageExtractor/examples/zenmuse_xtr.jpg
"thermo_nerf/__init__,py"
thermo_nerf/model_type.py
thermo_nerf/rendered_image_modalities.py
thermo_nerf/thermal_as_rgb.py
thermo_nerf/evaluator/evaluator.py
thermo_nerf/nerfacto_config/config_nerfacto.py
thermo_nerf/nerfacto_config/thermal_nerfacto.py
thermo_nerf/nerfstudio_config/pipeline_tracking.py
thermo_nerf/render/renderer.py
thermo_nerf/rgb_concat/concat_dataset.py
thermo_nerf/rgb_concat/concat_field.py
thermo_nerf/rgb_concat/concat_nerfacto_model.py
thermo_nerf/rgb_concat/config_concat_nerfacto.py
thermo_nerf/rgb_concat/rgbt_renderer.py
thermo_nerf/scripts/eval_script.py
thermo_nerf/scripts/images_to_nerf_dataset.py
thermo_nerf/scripts/render_video_script.py
thermo_nerf/scripts/thermal_viewer.py
thermo_nerf/scripts/train_eval_script.py
thermo_nerf/thermal_nerf/calculate_threshold.py
thermo_nerf/thermal_nerf/config_thermal_nerf.py
thermo_nerf/thermal_nerf/thermal_dataparser.py
thermo_nerf/thermal_nerf/thermal_dataset.py
thermo_nerf/thermal_nerf/thermal_field.py
thermo_nerf/thermal_nerf/thermal_field_head.py
thermo_nerf/thermal_nerf/thermal_metrics.py
thermo_nerf/thermal_nerf/thermal_nerf_model.py
thermo_nerf/thermal_nerf/thermal_renderer.py
thermo_scenes/update_colmap_json.py
thermo_scenes/docs/Collect_new_dataset.md
thermo_scenes/docs/images/align_bar.jpeg
thermo_scenes/docs/images/align_button.jpeg
thermo_scenes/flir_thermal_images/custom_flir.py
thermo_scenes/flir_thermal_images/thermal_visualiser.py
thermo_scenes/scripts/colorize_thermal_images.py
thermo_scenes/scripts/evaluate_camera_precision.py
thermo_scenes/scripts/images_to_nerf_dataset.py
thermo_scenes/scripts/modify_json.py
thermo_scenes/scripts/preprocess_thermal.py
thermo_scenes/scripts/rename_files.py
thermo_nerf-1.0.0.dist-info/METADATA
thermo_nerf-1.0.0.dist-info/WHEEL
thermo_nerf-1.0.0.dist-info/entry_points.txt
thermo_nerf-1.0.0.dist-info/licenses/LICENSE.pdf
thermo_nerf-1.0.0.dist-info/RECORD
