Metadata-Version: 2.4
Name: thermo-nerf
Version: 1.0.0
Summary: thermo-nerf
License-File: LICENSE.pdf
Keywords: flir,mlflow,nerf,pytorch,thermal
Requires-Python: >=3.10
Requires-Dist: mlflow>=2.11.1
Requires-Dist: nerfstudio>=1.1.5
Provides-Extra: flir
Requires-Dist: flirimageextractor>=1.5.3; extra == 'flir'
